sboxpresent/rtl/sbox.v
module sbox(input  wire [3:0] in, 
	    output reg  [3:0] out);

   always @ (in) begin
      case (in)
	4'h0: out = 4'hc;
	4'h1: out = 4'h5;
	4'h2: out = 4'h6;
	4'h3: out = 4'hb;
	4'h4: out = 4'h9;
	4'h5: out = 4'h0;
	4'h6: out = 4'hA;
	4'h7: out = 4'hD;
	4'h8: out = 4'h3;
	4'h9: out = 4'hE;
	4'ha: out = 4'hF;
	4'hb: out = 4'h8;
	4'hc: out = 4'h4;
	4'hd: out = 4'h7;
	4'he: out = 4'h1;
	4'hf: out = 4'h2;
	default: out = 4'h0;
      endcase
   end
   
endmodule

sboxpresent/sim/sboxtb.v
`timescale 1ns/1ps

module toptb();
   reg  [3:0]  in;   
   wire [3:0] out;
   
   sbox dut(.in(in), .out(out));
   
   initial
     begin
	
	$dumpfile("trace.vcd");
	$dumpvars(0, toptb);
	
	in = 4'b0;
	
	repeat (16) 
	  begin
	     #5;

	     $display("%x -> %x", in, out);
	     in = in + 4'b1;	     
	  end
	
	$finish;
   end
   
endmodule

sboxpresent/sim/trace.vcd
$date
	Thu May 11 11:33:56 2023
$end
$version
	Icarus Verilog
$end
$timescale
	1ps
$end
$scope module toptb $end
$var wire 4 ! out [3:0] $end
$var reg 4 " in [3:0] $end
$scope module dut $end
$var wire 4 # in [3:0] $end
$var reg 4 $ out [3:0] $end
$upscope $end
$upscope $end
$enddefinitions $end
#0
$dumpvars
b1100 $
b0 #
b0 "
b1100 !
$end
#5000
b101 !
b101 $
b1 "
b1 #
#10000
b110 !
b110 $
b10 "
b10 #
#15000
b1011 !
b1011 $
b11 "
b11 #
#20000
b1001 !
b1001 $
b100 "
b100 #
#25000
b0 !
b0 $
b101 "
b101 #
#30000
b1010 !
b1010 $
b110 "
b110 #
#35000
b1101 !
b1101 $
b111 "
b111 #
#40000
b11 !
b11 $
b1000 "
b1000 #
#45000
b1110 !
b1110 $
b1001 "
b1001 #
#50000
b1111 !
b1111 $
b1010 "
b1010 #
#55000
b1000 !
b1000 $
b1011 "
b1011 #
#60000
b100 !
b100 $
b1100 "
b1100 #
#65000
b111 !
b111 $
b1101 "
b1101 #
#70000
b1 !
b1 $
b1110 "
b1110 #
#75000
b10 !
b10 $
b1111 "
b1111 #
#80000
b1100 !
b1100 $
b0 "
b0 #
